readquant/__init__.py
readquant/data.py
readquant/parse.py
readquant/utils.py
readquant-1.2.0.data/scripts/fetch_reference.py
readquant-1.2.0.data/scripts/gather_bio_qc.py
readquant-1.2.0.data/scripts/gather_expression.py
readquant-1.2.0.data/scripts/gather_tech_qc.py
readquant-1.2.0.dist-info/DESCRIPTION.rst
readquant-1.2.0.dist-info/METADATA
readquant-1.2.0.dist-info/RECORD
readquant-1.2.0.dist-info/WHEEL
readquant-1.2.0.dist-info/metadata.json
readquant-1.2.0.dist-info/top_level.txt
