Metadata-Version: 2.0
Name: readquant
Version: 1.2.0
Summary: Convenience package for parsing RNA-seq quantification results
Home-page: UNKNOWN
Author: Valentine Svensson
Author-email: valentine@nxn.se
License: MIT
Platform: UNKNOWN
Requires-Dist: pandas
Requires-Dist: tqdm
